{
    "1": [
        { "name": "jack", "phone": 18616911410 },
        { "name": "jack", "phone": 18616911410 },
        { "name": "jack", "phone": 18616911410 },
        { "name": "jack", "phone": 18616911410 },
        { "name": "jack", "phone": 18616911410 },
        { "name": "jack", "phone": 18616911410 }
    ],
    "2": [
        { "name": "zy", "phone": 18616911410 },
        { "name": "zy", "phone": 18616911410 },
        { "name": "zy", "phone": 18616911410 },
        { "name": "zy", "phone": 18616911410 },
        { "name": "zy", "phone": 18616911410 },
        { "name": "zy", "phone": 18616911410 }
    ]
}